.gitignore
.travis.yml
CHANGES.txt
LICENSE.txt
MANIFEST.in
README.md
setup.py
kaiju/__init__.py
kaiju/arguments.py
kaiju/cli.py
kaiju.egg-info/PKG-INFO
kaiju.egg-info/SOURCES.txt
kaiju.egg-info/dependency_links.txt
kaiju.egg-info/requires.txt
kaiju.egg-info/top_level.txt
kaiju/tests/__init__.py
kaiju/tests/kaiju_tests.py
kaiju/tests/little_app.py