Metadata-Version: 1.0
Name: kaiju
Version: 0.1.0
Summary: Data analysis framework to log operations and interface with MongoDB.
Home-page: http://www.geekie.com.br
Author: Geekie
Author-email: geekie@geekie.com.br
License: UNKNOWN
Platform: UNKNOWN
